<?xml version="1.0"?>
<CONTROL_BASE>
	<Frequency name="Frequency" value="1000">
		<description>Benzetim Calisma Frekansi</description>
	</Frequency>
	<Duration name="Duration" value="100">
		<description>Benzetim Calisma Suresi</description>
	</Duration>
</CONTROL_BASE>
<LOG_VARIABLES>
	<Log_Variable name="ballPos" LogType="0" Frequency="1000" StartTime="0" Duration="100" Rows="1" Columns="3" />
	<Log_Variable name="ballScale" LogType="0" Frequency="1000" StartTime="0" Duration="100" Rows="1" Columns="3" />
	<Log_Variable name="xyTest" LogType="0" Frequency="1000" StartTime="0" Duration="100" Rows="1" Columns="2" />
	<Log_Variable name="totalBounceCount" LogType="0" Frequency="1000" StartTime="0" Duration="100" Rows="1" Columns="1" />
	<Log_Variable name="currentBounceCount" LogType="0" Frequency="1000" StartTime="0" Duration="100" Rows="1" Columns="1" />
	<Log_Variable name="velocity" LogType="0" Frequency="1000" StartTime="0" Duration="100" Rows="1" Columns="1" />
	<Log_Variable name="acc" LogType="0" Frequency="1000" StartTime="0" Duration="100" Rows="1" Columns="1" />
	<Log_Variable name="hitAcc" LogType="0" Frequency="1000" StartTime="0" Duration="100" Rows="1" Columns="1" />
	<Log_Variable name="radius" LogType="0" Frequency="1000" StartTime="0" Duration="100" Rows="1" Columns="1" />
</LOG_VARIABLES>
<CONTROL_VARIABLES>
	<Control_Variable name="hitAcc2" Rows="1" Columns="1">
		<Value value="0" />
	</Control_Variable>
	<Control_Variable name="gravity" Rows="1" Columns="1">
		<Value value="3" />
	</Control_Variable>
	<Control_Variable name="ballRadius" Rows="1" Columns="1">
		<Value value="7" />
	</Control_Variable>
</CONTROL_VARIABLES>
<MAIN_WINDOW X="62" Y="527" H="310" W="400" />
<WATCH_WINDOWS>
	<Watch_Window LogVariable="totalBounceCount" X="938" Y="582" W="155" H="45" BackGroundColor="56" SevenSegmentColor="63" Precision="4" />
</WATCH_WINDOWS>
<PLOT_WINDOWS>
	<PlotWindow X="734" Y="194" W="600" H="300" AutoScale="true" AutoTranslate="false">
		<Lines>
			<Line LogVariable="ballPos" Index="0" R="255" G="186" B="20" />
			<Line LogVariable="ballPos" Index="1" R="219" G="58" B="15" />
			<Line LogVariable="ballPos" Index="2" R="161" G="0" B="61" />
		</Lines>
	</PlotWindow>
</PLOT_WINDOWS>
<PLOT_XY_WINDOWS />
<SCENE_WINDOWS>
	<SceneWindow X="622" Y="438" W="670" H="655">
		<Vrml_Files>
			<File Path="/home/husnu/Desktop/BounceBall/vrbounce.wrl" />
		</Vrml_Files>
		<Binded_Vars Variable_Count="4">
			<Binded_Variable Filename="vrbounce.wrl" Variable="radius" Variable_Index="0" vrmlIndexCount="4">
				<Vrml_Indexes Value="1" Value="5" Value="1" Value="0" />
			</Binded_Variable>
			<Binded_Variable Filename="vrbounce.wrl" Variable="ballScale" Variable_Index="0" vrmlIndexCount="3">
				<Vrml_Indexes Value="1" Value="2" Value="0" />
			</Binded_Variable>
			<Binded_Variable Filename="vrbounce.wrl" Variable="ballScale" Variable_Index="1" vrmlIndexCount="3">
				<Vrml_Indexes Value="1" Value="2" Value="1" />
			</Binded_Variable>
			<Binded_Variable Filename="vrbounce.wrl" Variable="ballScale" Variable_Index="2" vrmlIndexCount="3">
				<Vrml_Indexes Value="1" Value="2" Value="2" />
			</Binded_Variable>
		</Binded_Vars>
	</SceneWindow>
</SCENE_WINDOWS>
